b2_plotter/Plotter.py
b2_plotter/__init__.py
b2_plotter/example.ipynb
b2_plotter/test_project.py
b2_plotter-4.0.5.dist-info/METADATA
b2_plotter-4.0.5.dist-info/WHEEL
b2_plotter-4.0.5.dist-info/licenses/LICENSE.txt
b2_plotter-4.0.5.dist-info/RECORD
