Metadata-Version: 2.1
Name: b2_plotter
Version: 4.0.5
Summary: A simple Python package for use by Belle II analysts to make various plots out of pandas dataframes and numpy arrays.
Project-URL: Homepage, https://github.com/psgebeline/b2_plotter
Project-URL: Bug Tracker, https://github.com/psgebeline/b2_plotter/issues
Author-email: Paul Gebeline <paulgebeline1@gmail.com>
License-File: LICENSE.txt
Classifier: License :: OSI Approved :: MIT License
Classifier: Operating System :: OS Independent
Classifier: Programming Language :: Python :: 3
Requires-Python: >=3.7
